{
  "results_root": "results",
  "zero_shot_root": "results",
  "run_subdir": "train_alignn_fromscratch_epochs100_bs32_lr5e5",
  "runs_csv": "reports/Hyperparameter Set 3/Summaries/From Scratch/fromscratch_runs.csv",
  "summary_csv": "reports/Hyperparameter Set 3/Summaries/From Scratch/fromscratch_summary.csv",
  "seeds": [
    0,
    1,
    2,
    3,
    4
  ],
  "plots": {
    "oxide": {
      "png": "reports/Hyperparameter Set 3/Comparison Plots/Oxide Comparison Plot - Hyperparameter Set 3.png",
      "pdf": "reports/Hyperparameter Set 3/Comparison Plots/Oxide Comparison Plot - Hyperparameter Set 3.pdf"
    },
    "nitride": {
      "png": "reports/Hyperparameter Set 3/Comparison Plots/Nitride Comparison Plot - Hyperparameter Set 3.png",
      "pdf": "reports/Hyperparameter Set 3/Comparison Plots/Nitride Comparison Plot - Hyperparameter Set 3.pdf"
    }
  }
}
